pgx/__init__.py
pgx/animal_shogi.py
pgx/backgammon.py
pgx/bridge_bidding.py
pgx/chess.py
pgx/connect_four.py
pgx/core.py
pgx/gardner_chess.py
pgx/go.py
pgx/hex.py
pgx/kuhn_poker.py
pgx/leduc_holdem.py
pgx/othello.py
pgx/play2048.py
pgx/shogi.py
pgx/sparrow_mahjong.py
pgx/tic_tac_toe.py
pgx/_src/__init__.py
pgx/_src/api_test.py
pgx/_src/baseline.py
pgx/_src/gardner_chess_utils.py
pgx/_src/struct.py
pgx/_src/types.py
pgx/_src/utils.py
pgx/_src/visualizer.py
pgx/_src/dwg/__init__.py
pgx/_src/dwg/animalshogi.py
pgx/_src/dwg/backgammon.py
pgx/_src/dwg/bridge_bidding.py
pgx/_src/dwg/chess.py
pgx/_src/dwg/connect_four.py
pgx/_src/dwg/gardner_chess.py
pgx/_src/dwg/go.py
pgx/_src/dwg/hex.py
pgx/_src/dwg/kuhn_poker.py
pgx/_src/dwg/leduc_holdem.py
pgx/_src/dwg/mahjong.py
pgx/_src/dwg/mahjong_tile.py
pgx/_src/dwg/othello.py
pgx/_src/dwg/play2048.py
pgx/_src/dwg/shogi.py
pgx/_src/dwg/sparrow_mahjong.py
pgx/_src/dwg/tictactoe.py
pgx/_src/dwg/images/__init__.py
pgx/_src/dwg/images/chess/LICENSE
pgx/_src/dwg/images/chess/__init__.py
pgx/_src/dwg/images/chess/bBishop.svg
pgx/_src/dwg/images/chess/bKing.svg
pgx/_src/dwg/images/chess/bKnight.svg
pgx/_src/dwg/images/chess/bPawn.svg
pgx/_src/dwg/images/chess/bQueen.svg
pgx/_src/dwg/images/chess/bRook.svg
pgx/_src/dwg/images/chess/wBishop.svg
pgx/_src/dwg/images/chess/wKing.svg
pgx/_src/dwg/images/chess/wKnight.svg
pgx/_src/dwg/images/chess/wPawn.svg
pgx/_src/dwg/images/chess/wQueen.svg
pgx/_src/dwg/images/chess/wRook.svg
pgx/_src/dwg/images/sparrow_mahjong/1p.svg
pgx/_src/dwg/images/sparrow_mahjong/1pr.svg
pgx/_src/dwg/images/sparrow_mahjong/2p.svg
pgx/_src/dwg/images/sparrow_mahjong/2pr.svg
pgx/_src/dwg/images/sparrow_mahjong/3p.svg
pgx/_src/dwg/images/sparrow_mahjong/3pr.svg
pgx/_src/dwg/images/sparrow_mahjong/4p.svg
pgx/_src/dwg/images/sparrow_mahjong/4pr.svg
pgx/_src/dwg/images/sparrow_mahjong/5p.svg
pgx/_src/dwg/images/sparrow_mahjong/5pr.svg
pgx/_src/dwg/images/sparrow_mahjong/6p.svg
pgx/_src/dwg/images/sparrow_mahjong/6pr.svg
pgx-2.6.0.dist-info/LICENSE
pgx-2.6.0.dist-info/METADATA
pgx-2.6.0.dist-info/WHEEL
pgx-2.6.0.dist-info/top_level.txt
pgx-2.6.0.dist-info/RECORD
