Metadata-Version: 2.2
Name: pgx
Version: 2.6.0
Home-page: https://github.com/sotetsuk/pgx
Author: Sotetsu KOYAMADA
Author-email: sotetsu.koyamada@gmail.com
Classifier: Programming Language :: Python :: 3.9
Classifier: Programming Language :: Python :: 3.10
Classifier: Programming Language :: Python :: 3.11
Classifier: Programming Language :: Python :: 3.12
Classifier: Programming Language :: Python :: 3.13
License-File: LICENSE
Requires-Dist: jax>=0.4.6
Requires-Dist: typing_extensions>=4.2.0
Requires-Dist: svgwrite
Dynamic: author
Dynamic: author-email
Dynamic: classifier
Dynamic: description
Dynamic: description-content-type
Dynamic: home-page
Dynamic: keywords
Dynamic: requires-dist
